Workbook

Sheet Customer_Data
A1: customer_id | B1: customer_name | C1: product_type | D1: fresco_segment | E1: age_band | F1: region | G1: days_to_maturity | H1: active_dd | I1: failed_dd | J1: account_value | K1: online_login_days | L1: complaints | M1: previous_campaign_response | N1: email_open_rate | O1: web_visits_30d | P1: has_adviser | Q1: segment_weight | R1: conversion_score | S1: priority | T1: next_best_action
A2: 200001 | B2: Mia Wilson | C2: ISA | D2: Retired Security Seekers | E2: 18-24 | F2: South West | G2: 53 | H2: No | I2: No | J2: 3348 | K2: 152 | L2: 0 | M2: Yes | N2: 0.19 | O2: 8 | P2: No | Q2: =VLOOKUP(D2,Segment_Lookup!$A$2:$D$9,4,FALSE) -> 10 | R2: =IF(G2<=30,30,IF(G2<=90,20,IF(G2<=180,10,0)))+IF(H2="Yes",15,0)+IF(I2="Yes",-15,0)+IF(J2>=15000,25,IF(J2>=10000,20,IF(J2>=5000,10,0)))+IF(K2<=30,15,IF(K2<=90,8,0))+IF(L2=0,10,IF(L2>=2,-20,0))+IF(M2="Yes",15,0)+IF(N2>=0.5,10,0)+IF(O2>=3,10,0)+Q2 -> 65 | S2: =IF(R2>=85,"Very High",IF(R2>=65,"High",IF(R2>=40,"Medium","Low"))) -> High | T2: =IF(S2="Very High","Priority outbound call",IF(S2="High","Outbound call",IF(AND(S2="Medium",N2>=0.4),"Email then call","Digital nurture"))) -> Outbound call
A3: 200002 | B3: Mia Thompson | C3: ISA | D3: Cautious Savers | E3: 65+ | F3: East of England | G3: 143 | H3: No | I3: Yes | J3: 26905 | K3: 41 | L3: 1 | M3: No | N3: 0.13 | O3: 12 | P3: No | Q3: =VLOOKUP(D3,Segment_Lookup!$A$2:$D$9,4,FALSE) -> 8 | R3: =IF(G3<=30,30,IF(G3<=90,20,IF(G3<=180,10,0)))+IF(H3="Yes",15,0)+IF(I3="Yes",-15,0)+IF(J3>=15000,25,IF(J3>=10000,20,IF(J3>=5000,10,0)))+IF(K3<=30,15,IF(K3<=90,8,0))+IF(L3=0,10,IF(L3>=2,-20,0))+IF(M3="Yes",15,0)+IF(N3>=0.5,10,0)+IF(O3>=3,10,0)+Q3 -> 46 | S3: =IF(R3>=85,"Very High",IF(R3>=65,"High",IF(R3>=40,"Medium","Low"))) -> Medium | T3: =IF(S3="Very High","Priority outbound call",IF(S3="High","Outbound call",IF(AND(S3="Medium",N3>=0.4),"Email then call","Digital nurture"))) -> Digital nurture
A4: 200003 | B4: Grace Evans | C4: CTF | D4: Digital Natives | E4: 18-24 | F4: South East | G4: 236 | H4: Yes | I4: No | J4: 12903 | K4: 21 | L4: 1 | M4: No | N4: 0.53 | O4: 5 | P4: No | Q4: =VLOOKUP(D4,Segment_Lookup!$A$2:$D$9,4,FALSE) -> 13 | R4: =IF(G4<=30,30,IF(G4<=90,20,IF(G4<=180,10,0)))+IF(H4="Yes",15,0)+IF(I4="Yes",-15,0)+IF(J4>=15000,25,IF(J4>=10000,20,IF(J4>=5000,10,0)))+IF(K4<=30,15,IF(K4<=90,8,0))+IF(L4=0,10,IF(L4>=2,-20,0))+IF(M4="Yes",15,0)+IF(N4>=0.5,10,0)+IF(O4>=3,10,0)+Q4 -> 83 | S4: =IF(R4>=85,"Very High",IF(R4>=65,"High",IF(R4>=40,"Medium","Low"))) -> High | T4: =IF(S4="Very High","Priority outbound call",IF(S4="High","Outbound call",IF(AND(S4="Medium",N4>=0.4),"Email then call","Digital nurture"))) -> Outbound call
A5: 200004 | B5: Sophia Jones | C5: ISA | D5: Budget Conscious | E5: 18-24 | F5: North West | G5: 52 | H5: Yes | I5: No | J5: 27832 | K5: 94 | L5: 0 | M5: No | N5: 0.57 | O5: 11 | P5: No | Q5: =VLOOKUP(D5,Segment_Lookup!$A$2:$D$9,4,FALSE) -> 5 | R5: =IF(G5<=30,30,IF(G5<=90,20,IF(G5<=180,10,0)))+IF(H5="Yes",15,0)+IF(I5="Yes",-15,0)+IF(J5>=15000,25,IF(J5>=10000,20,IF(J5>=5000,10,0)))+IF(K5<=30,15,IF(K5<=90,8,0))+IF(L5=0,10,IF(L5>=2,-20,0))+IF(M5="Yes",15,0)+IF(N5>=0.5,10,0)+IF(O5>=3,10,0)+Q5 -> 95 | S5: =IF(R5>=85,"Very High",IF(R5>=65,"High",IF(R5>=40,"Medium","Low"))) -> Very High | T5: =IF(S5="Very High","Priority outbound call",IF(S5="High","Outbound call",IF(AND(S5="Medium",N5>=0.4),"Email then call","Digital nurture"))) -> Priority outbound call
A6: 200005 | B6: Evie Wilson | C6: ISA | D6: Rising Professionals | E6: 55-64 | F6: South West | G6: 237 | H6: Yes | I6: No | J6: 21471 | K6: 177 | L6: 1 | M6: No | N6: 0.72 | O6: 12 | P6: Yes | Q6: =VLOOKUP(D6,Segment_Lookup!$A$2:$D$9,4,FALSE) -> 14 | R6: =IF(G6<=30,30,IF(G6<=90,20,IF(G6<=180,10,0)))+IF(H6="Yes",15,0)+IF(I6="Yes",-15,0)+IF(J6>=15000,25,IF(J6>=10000,20,IF(J6>=5000,10,0)))+IF(K6<=30,15,IF(K6<=90,8,0))+IF(L6=0,10,IF(L6>=2,-20,0))+IF(M6="Yes",15,0)+IF(N6>=0.5,10,0)+IF(O6>=3,10,0)+Q6 -> 74 | S6: =IF(R6>=85,"Very High",IF(R6>=65,"High",IF(R6>=40,"Medium","Low"))) -> High | T6: =IF(S6="Very High","Priority outbound call",IF(S6="High","Outbound call",IF(AND(S6="Medium",N6>=0.4),"Email then call","Digital nurture"))) -> Outbound call
A7: 200006 | B7: Oscar Jones | C7: Over 50 | D7: Cautious Savers | E7: 65+ | F7: North West | G7: 291 | H7: No | I7: No | J7: 21977 | K7: 128 | L7: 0 | M7: No | N7: 0.39 | O7: 4 | P7: Yes | Q7: =VLOOKUP(D7,Segment_Lookup!$A$2:$D$9,4,FALSE) -> 8 | R7: =IF(G7<=30,30,IF(G7<=90,20,IF(G7<=180,10,0)))+IF(H7="Yes",15,0)+IF(I7="Yes",-15,0)+IF(J7>=15000,25,IF(J7>=10000,20,IF(J7>=5000,10,0)))+IF(K7<=30,15,IF(K7<=90,8,0))+IF(L7=0,10,IF(L7>=2,-20,0))+IF(M7="Yes",15,0)+IF(N7>=0.5,10,0)+IF(O7>=3,10,0)+Q7 -> 53 | S7: =IF(R7>=85,"Very High",IF(R7>=65,"High",IF(R7>=40,"Medium","Low"))) -> Medium | T7: =IF(S7="Very High","Priority outbound call",IF(S7="High","Outbound call",IF(AND(S7="Medium",N7>=0.4),"Email then call","Digital nurture"))) -> Digital nurture
A8: 200007 | B8: Thomas Wright | C8: ISA | D8: Retired Security Seekers | E8: 55-64 | F8: East of England | G8: 205 | H8: Yes | I8: No | J8: 5032 | K8: 131 | L8: 0 | M8: No | N8: 0.73 | O8: 2 | P8: No | Q8: =VLOOKUP(D8,Segment_Lookup!$A$2:$D$9,4,FALSE) -> 10 | R8: =IF(G8<=30,30,IF(G8<=90,20,IF(G8<=180,10,0)))+IF(H8="Yes",15,0)+IF(I8="Yes",-15,0)+IF(J8>=15000,25,IF(J8>=10000,20,IF(J8>=5000,10,0)))+IF(K8<=30,15,IF(K8<=90,8,0))+IF(L8=0,10,IF(L8>=2,-20,0))+IF(M8="Yes",15,0)+IF(N8>=0.5,10,0)+IF(O8>=3,10,0)+Q8 -> 55 | S8: =IF(R8>=85,"Very High",IF(R8>=65,"High",IF(R8>=40,"Medium","Low"))) -> Medium | T8: =IF(S8="Very High","Priority outbound call",IF(S8="High","Outbound call",IF(AND(S8="Medium",N8>=0.4),"Email then call","Digital nurture"))) -> Email then call
A9: 200008 | B9: Jack Walker | C9: ISA | D9: Comfortable Families | E9: 45-54 | F9: East of England | G9: 240 | H9: Yes | I9: No | J9: 28706 | K9: 3 | L9: 1 | M9: Yes | N9: 0.75 | O9: 12 | P9: No | Q9: =VLOOKUP(D9,Segment_Lookup!$A$2:$D$9,4,FALSE) -> 12 | R9: =IF(G9<=30,30,IF(G9<=90,20,IF(G9<=180,10,0)))+IF(H9="Yes",15,0)+IF(I9="Yes",-15,0)+IF(J9>=15000,25,IF(J9>=10000,20,IF(J9>=5000,10,0)))+IF(K9<=30,15,IF(K9<=90,8,0))+IF(L9=0,10,IF(L9>=2,-20,0))+IF(M9="Yes",15,0)+IF(N9>=0.5,10,0)+IF(O9>=3,10,0)+Q9 -> 102 | S9: =IF(R9>=85,"Very High",IF(R9>=65,"High",IF(R9>=40,"Medium","Low"))) -> Very High | T9: =IF(S9="Very High","Priority outbound call",IF(S9="High","Outbound call",IF(AND(S9="Medium",N9>=0.4),"Email then call","Digital nurture"))) -> Priority outbound call
A10: 200009 | B10: Freya Brown | C10: ISA | D10: Retired Security Seekers | E10: 18-24 | F10: Wales | G10: 2 | H10: No | I10: No | J10: 9130 | K10: 129 | L10: 1 | M10: No | N10: 0.09 | O10: 10 | P10: No | Q10: =VLOOKUP(D10,Segment_Lookup!$A$2:$D$9,4,FALSE) -> 10 | R10: =IF(G10<=30,30,IF(G10<=90,20,IF(G10<=180,10,0)))+IF(H10="Yes",15,0)+IF(I10="Yes",-15,0)+IF(J10>=15000,25,IF(J10>=10000,20,IF(J10>=5000,10,0)))+IF(K10<=30,15,IF(K10<=90,8,0))+IF(L10=0,10,IF(L10>=2,-20,0))+IF(M10="Yes",15,0)+IF(N10>=0.5,10,0)+IF(O10>=3,10,0)+Q10 -> 60 | S10: =IF(R10>=85,"Very High",IF(R10>=65,"High",IF(R10>=40,"Medium","Low"))) -> Medium | T10: =IF(S10="Very High","Priority outbound call",IF(S10="High","Outbound call",IF(AND(S10="Medium",N10>=0.4),"Email then call","Digital nurture"))) -> Digital nurture
A11: 200010 | B11: Muhammad Roberts | C11: ISA | D11: Budget Conscious | E11: 55-64 | F11: South West | G11: 277 | H11: No | I11: No | J11: 518 | K11: 154 | L11: 0 | M11: Yes | N11: 0.79 | O11: 12 | P11: No | Q11: =VLOOKUP(D11,Segment_Lookup!$A$2:$D$9,4,FALSE) -> 5 | R11: =IF(G11<=30,30,IF(G11<=90,20,IF(G11<=180,10,0)))+IF(H11="Yes",15,0)+IF(I11="Yes",-15,0)+IF(J11>=15000,25,IF(J11>=10000,20,IF(J11>=5000,10,0)))+IF(K11<=30,15,IF(K11<=90,8,0))+IF(L11=0,10,IF(L11>=2,-20,0))+IF(M11="Yes",15,0)+IF(N11>=0.5,10,0)+IF(O11>=3,10,0)+Q11 -> 50 | S11: =IF(R11>=85,"Very High",IF(R11>=65,"High",IF(R11>=40,"Medium","Low"))) -> Medium | T11: =IF(S11="Very High","Priority outbound call",IF(S11="High","Outbound call",IF(AND(S11="Medium",N11>=0.4),"Email then call","Digital nurture"))) -> Email then call
A12: 200011 | B12: Noah White | C12: CTF | D12: Comfortable Families | E12: 55-64 | F12: London | G12: 273 | H12: No | I12: Yes | J12: 16074 | K12: 141 | L12: 0 | M12: No | N12: 0.52 | O12: 3 | P12: No | Q12: =VLOOKUP(D12,Segment_Lookup!$A$2:$D$9,4,FALSE) -> 12 | R12: =IF(G12<=30,30,IF(G12<=90,20,IF(G12<=180,10,0)))+IF(H12="Yes",15,0)+IF(I12="Yes",-15,0)+IF(J12>=15000,25,IF(J12>=10000,20,IF(J12>=5000,10,0)))+IF(K12<=30,15,IF(K12<=90,8,0))+IF(L12=0,10,IF(L12>=2,-20,0))+IF(M12="Yes",15,0)+IF(N12>=0.5,10,0)+IF(O12>=3,10,0)+Q12 -> 52 | S12: =IF(R12>=85,"Very High",IF(R12>=65,"High",IF(R12>=40,"Medium","Low"))) -> Medium | T12: =IF(S12="Very High","Priority outbound call",IF(S12="High","Outbound call",IF(AND(S12="Medium",N12>=0.4),"Email then call","Digital nurture"))) -> Email then call
A13: 200012 | B13: Sophia Walker | C13: ISA | D13: Budget Conscious | E13: 65+ | F13: East Midlands | G13: 225 | H13: No | I13: No | J13: 8623 | K13: 58 | L13: 0 | M13: Yes | N13: 0.47 | O13: 9 | P13: No | Q13: =VLOOKUP(D13,Segment_Lookup!$A$2:$D$9,4,FALSE) -> 5 | R13: =IF(G13<=30,30,IF(G13<=90,20,IF(G13<=180,10,0)))+IF(H13="Yes",15,0)+IF(I13="Yes",-15,0)+IF(J13>=15000,25,IF(J13>=10000,20,IF(J13>=5000,10,0)))+IF(K13<=30,15,IF(K13<=90,8,0))+IF(L13=0,10,IF(L13>=2,-20,0))+IF(M13="Yes",15,0)+IF(N13>=0.5,10,0)+IF(O13>=3,10,0)+Q13 -> 58 | S13: =IF(R13>=85,"Very High",IF(R13>=65,"High",IF(R13>=40,"Medium","Low"))) -> Medium | T13: =IF(S13="Very High","Priority outbound call",IF(S13="High","Outbound call",IF(AND(S13="Medium",N13>=0.4),"Email then call","Digital nurture"))) -> Email then call
... A101: 200100 | B101: Mia Walker | C101: ISA | D101: Digital Natives | E101: 45-54 | F101: London | G101: 192 | H101: Yes | I101: No | J101: 3746 | K101: 215 | L101: 1 | M101: No | N101: 0.12 | O101: 0 | P101: No | Q101: =VLOOKUP(D101,Segment_Lookup!$A$2:$D$9,4,FALSE) -> 13 | R101: =IF(G101<=30,30,IF(G101<=90,20,IF(G101<=180,10,0)))+IF(H101="Yes",15,0)+IF(I101="Yes",-15,0)+IF(J101>=15000,25,IF(J101>=10000,20,IF(J101>=5000,10,0)))+IF(K101<=30,15,IF(K101<=90,8,0))+IF(L101=0,10,IF(L101>=2,-20,0))+IF(M101="Yes",15,0)+IF(N101>=0.5,10,0)+IF(O101>=3,10,0)+Q101 -> 28 | S101: =IF(R101>=85,"Very High",IF(R101>=65,"High",IF(R101>=40,"Medium","Low"))) -> Low | T101: =IF(S101="Very High","Priority outbound call",IF(S101="High","Outbound call",IF(AND(S101="Medium",N101>=0.4),"Email then call","Digital nurture"))) -> Digital nurture

Sheet Segment_Lookup
A1: Fresco_Segment | B1: Segment_Group | C1: Profile_Summary | D1: Segment_Weight
A2: Affluent Achievers | B2: Affluent | C2: High income, investment-aware households | D2: 15
A3: Comfortable Families | B3: Family Growth | C3: Family-focused customers with savings potential | D3: 12
A4: Rising Professionals | B4: Emerging Wealth | C4: Digitally engaged younger professionals | D4: 14
A5: Budget Conscious | B5: Value Seekers | C5: Cost-sensitive customers requiring clear value messages | D5: 5
A6: Retired Security Seekers | B6: Retirement Focus | C6: Older customers focused on security and income | D6: 10
A7: Digital Natives | B7: Digital First | C7: Highly digitally engaged younger customers | D7: 13
A8: Cautious Savers | B8: Conservative | C8: Low-risk savers who prefer reassurance | D8: 8
A9: Mass Market Mainstream | B9: Mainstream | C9: Average financial engagement and moderate value | D9: 7

Sheet Model_Rules
A1: Rule Area | B1: Logic | C1: Score Impact
A2: Maturity Date | B2: 0-30 days to maturity | C2: +30
A3: Maturity Date | B3: 31-90 days to maturity | C3: +20
A4: Maturity Date | B4: 91-180 days to maturity | C4: +10
A5: Active Direct Debit | B5: Active DD = Yes | C5: +15
A6: Failed Direct Debit | B6: Failed DD = Yes | C6: -15
A7: Account Value | B7: £15,000 or more | C7: +25
A8: Account Value | B8: £10,000 to £14,999 | C8: +20
A9: Account Value | B9: £5,000 to £9,999 | C9: +10
A10: Online Login | B10: Logged in within 30 days | C10: +15
A11: Online Login | B11: Logged in within 90 days | C11: +8
A12: Complaints | B12: 0 complaints | C12: +10
... A17: Segment Weight | B17: Based on Fresco-style segment | C17: +5 to +15

Sheet README
A1: Customer Segmentation & Next Best Action Model - Sample Dataset
A3: Purpose | B3: Create a portfolio-ready mock dataset using Fresco-style segmentation to prioritise outbound calling and next-best-action decisions.
A4: Important | B4: The segment labels are fictional Fresco-style examples for portfolio/demo use only, not official CACI Fresco data.
A5: How to use | B5: Use Customer_Data as input for Python model. Columns Q:T show Excel formula logic for segment weight, conversion score, priority and next best action.
A6: Next step | B6: Build the same scoring in Python, export a prioritised call file, then create Power BI visuals by segment/product/priority.
